[{"name":"Glasgow Branch","count":25,"data":[{"title":"Prince of Thorns","authors":"Mark Lawrence","price":8.99,"stock":25},{"title":"Stick","authors":"Elmore Leonard","price":8.99,"stock":15},{"title":"52 Pickup","authors":"Elmore Leonard","price":8.99,"stock":30},{"title":"King of Thorns","authors":"Mark Lawrence","price":8.99,"stock":50},{"title":"Emperor of Thorns","authors":"Mark Lawrence","price":8.99,"stock":48},{"title":"The Sisters Brothers","authors":"Patrick DeWitt","price":8.99,"stock":12},{"title":"The Essex Serpent","authors":"Sarah Perry","price":8.99,"stock":94},{"title":"Why I’m No Longer Talking to White People About Race","authors":"Reni Eddo-Lodge","price":8.99,"stock":82},{"title":"Cujo","authors":"Stephen King","price":8.99,"stock":12},{"title":"Blackbirds","authors":"Chuck Wendig","price":8.99,"stock":6},{"title":"Hollow Things","authors":"T.S. King","price":8.99,"stock":13},{"title":"Heart Shaped Box","authors":"Joe Hill","price":8.99,"stock":67},{"title":"Buddha Da","authors":"Anne Donovan","price":8.99,"stock":43},{"title":"Trainspotting","authors":"Irvine Welsh","price":8.99,"stock":21},{"title":"The Crow Road","authors":"Iain Banks","price":8.99,"stock":12},{"title":"Klara and the Sun","authors":"Kazuo Ishiguro","price":8.99,"stock":12},{"title":"One: Pot, Pan, Planet","authors":"Anna Jones","price":8.99,"stock":39},{"title":"The Midnight Library","authors":"Matt Haig","price":8.99,"stock":62},{"title":"Acts of Desperation","authors":"Megan Nolan","price":8.99,"stock":2},{"title":"Transcendant Kingdom","authors":"Yaa Gyasi","price":8.99,"stock":4},{"title":"Difficult Women","authors":"Helen Lewis","price":8.99,"stock":12},{"title":"With These Hands","authors":"Pam Ayres","price":8.99,"stock":49},{"title":"Empireland","authors":"Sathnam Sanghera","price":8.99,"stock":12},{"title":"The Thursday Murder Club","authors":"Richard Osman","price":8.99,"stock":23},{"title":"Luster","authors":"Raven Leilani","price":8.99,"stock":46}]},{"name":"Inverness Branch","count":25,"data":[{"title":"Prince of Thorns","authors":"Mark Lawrence","price":8.99,"stock":25},{"title":"Stick","authors":"Elmore Leonard","price":8.99,"stock":15},{"title":"52 Pickup","authors":"Elmore Leonard","price":8.99,"stock":30},{"title":"King of Thorns","authors":"Mark Lawrence","price":8.99,"stock":50},{"title":"Emperor of Thorns","authors":"Mark Lawrence","price":8.99,"stock":48},{"title":"The Sisters Brothers","authors":"Patrick DeWitt","price":8.99,"stock":12},{"title":"The Essex Serpent","authors":"Sarah Perry","price":8.99,"stock":94},{"title":"Why I’m No Longer Talking to White People About Race","authors":"Reni Eddo-Lodge","price":8.99,"stock":82},{"title":"Cujo","authors":"Stephen King","price":8.99,"stock":12},{"title":"Blackbirds","authors":"Chuck Wendig","price":8.99,"stock":6},{"title":"Hollow Things","authors":"T.S. King","price":8.99,"stock":13},{"title":"Heart Shaped Box","authors":"Joe Hill","price":8.99,"stock":67},{"title":"Buddha Da","authors":"Anne Donovan","price":8.99,"stock":43},{"title":"Trainspotting","authors":"Irvine Welsh","price":8.99,"stock":21},{"title":"The Crow Road","authors":"Iain Banks","price":8.99,"stock":12},{"title":"Klara and the Sun","authors":"Kazuo Ishiguro","price":8.99,"stock":12},{"title":"One: Pot, Pan, Planet","authors":"Anna Jones","price":8.99,"stock":39},{"title":"The Midnight Library","authors":"Matt Haig","price":8.99,"stock":62},{"title":"Acts of Desperation","authors":"Megan Nolan","price":8.99,"stock":2},{"title":"Transcendant Kingdom","authors":"Yaa Gyasi","price":8.99,"stock":4},{"title":"Difficult Women","authors":"Helen Lewis","price":8.99,"stock":12},{"title":"With These Hands","authors":"Pam Ayres","price":8.99,"stock":49},{"title":"Empireland","authors":"Sathnam Sanghera","price":8.99,"stock":12},{"title":"The Thursday Murder Club","authors":"Richard Osman","price":8.99,"stock":23},{"title":"Luster","authors":"Raven Leilani","price":8.99,"stock":46}]}]